[
    {
        "params": "nodejs",
        "name": "Node.js",
        "picSrc": "nodejs.svg",
        "desc": "Server",
        "status": "",
        "works": [
            {
                "name": "",
                "picSrc": "",
                "desc": [],
                "website": "",
                "github": ""
            },
            {}
        ]
    },
    {
        "params": "nuxtjs",
        "name": "Nuxt.js",
        "picSrc": "nuxtjs.svg",
        "desc": "Server",
        "status": "",
        "works": [
            {
                "name": "",
                "picSrc": "",
                "desc": [],
                "website": "",
                "github": ""
            },
            {}
        ]
    }
]